{"cameraMode":{"drawMode":0,"name":"Shaded","section":"Shading Mode"},"sceneLighting":false,"audioPlay":false,"sceneViewState":{"m_AlwaysRefresh":false,"showFog":true,"showSkybox":false,"showFlares":true,"showImageEffects":true,"showParticleSystems":true,"showVisualEffectGraphs":true,"m_FxEnabled":true},"in2DMode":false,"pivot":{"x":5.44645357131958,"y":7.096634864807129,"z":-4.5274882316589359},"rotation":{"x":0.1286487877368927,"y":-0.35735946893692019,"z":0.04968564584851265,"w":0.9240567088127136},"size":6.485427379608154,"orthographic":false}