{"cameraMode":{"drawMode":0,"name":"Shaded","section":"Shading Mode"},"sceneLighting":true,"audioPlay":false,"sceneViewState":{"m_AlwaysRefresh":false,"showFog":true,"showSkybox":true,"showFlares":true,"showImageEffects":true,"showParticleSystems":true,"showVisualEffectGraphs":true,"m_FxEnabled":true},"in2DMode":false,"pivot":{"x":-0.7953004837036133,"y":-13.212385177612305,"z":11.305035591125489},"rotation":{"x":0.27142244577407839,"y":0.31309694051742556,"z":-0.09388553351163864,"w":0.9052301645278931},"size":45.81922149658203,"orthographic":false}